expectigrad/__init__.py
expectigrad/pytorch.py
expectigrad/tensorflow1.py
expectigrad/tensorflow2.py
expectigrad/testing.py
expectigrad-0.0.0.dist-info/LICENSE
expectigrad-0.0.0.dist-info/METADATA
expectigrad-0.0.0.dist-info/WHEEL
expectigrad-0.0.0.dist-info/top_level.txt
expectigrad-0.0.0.dist-info/RECORD
