Metadata-Version: 2.1
Name: expectigrad
Version: 0.0.0
Summary: Expectigrad optimizer for Pytorch and TensorFlow
Home-page: https://github.com/brett-daley/expectigrad
Author: Brett Daley
Author-email: b.daley@northeastern.edu
License: UNKNOWN
Platform: UNKNOWN
Classifier: Programming Language :: Python :: 3
Classifier: License :: OSI Approved :: MIT License
Classifier: Operating System :: OS Independent
Requires-Python: >=3.5
